JKFF.v
module JKFF(J,K,clk,Q,reset);

input J,K,clk,reset;
output reg Q;

always @(posedge clk,posedge reset)begin
    if(reset) Q<=0;
    else begin
        if(J==0&&K==0) Q<=Q;
        else if(J==0&&K==1) Q<=0;
        else if(J==1&&K==0) Q<=1;
        else if(J==1&&K==1) Q<=~Q;
    end
end
endmodule

async_down_JKFF.v
`include "JKFF.v"
module async_down_JKFF(clk,Q,reset);

input clk, reset;
output [3:0] Q;

JKFF JKFF_ins1(1'b1,1'b1,clk,Q[0],reset);
JKFF JKFF_ins2(1'b1,1'b1,Q[0],Q[1],reset);
JKFF JKFF_ins3(1'b1,1'b1,Q[1],Q[2],reset);
JKFF JKFF_ins4(1'b1,1'b1,Q[2],Q[3],reset);
endmodule

async_down_JKFF_tb.v
`include "async_down_JKFF.v"
`timescale 1ns/1ns

module async_down_JKFF_tb();

reg clk, reset;
wire [3:0] Q;

async_down_JKFF async_down_JKFF_ins(clk,Q,reset);

initial begin
    $dumpfile("async_down_JKFF_tb.vcd");
    $dumpvars(0,async_down_JKFF_tb);
end

initial begin
    clk = 0;
    forever #2 clk = ~clk;
end

initial begin
    reset = 1; #2;
    reset = 0; #62;
    $finish;
end
endmodule

async_down_JKFF_tb.vcd
$date
	Tue Nov 04 23:57:21 2025
$end
$version
	Icarus Verilog
$end
$timescale
	1ns
$end
$scope module async_down_JKFF_tb $end
$var wire 4 ! Q [3:0] $end
$var reg 1 " clk $end
$var reg 1 # reset $end
$scope module async_down_JKFF_ins $end
$var wire 1 " clk $end
$var wire 1 # reset $end
$var wire 4 $ Q [3:0] $end
$scope module JKFF_ins1 $end
$var wire 1 % J $end
$var wire 1 & K $end
$var wire 1 " clk $end
$var wire 1 # reset $end
$var reg 1 ' Q $end
$upscope $end
$scope module JKFF_ins2 $end
$var wire 1 ( J $end
$var wire 1 ) K $end
$var wire 1 * clk $end
$var wire 1 # reset $end
$var reg 1 + Q $end
$upscope $end
$scope module JKFF_ins3 $end
$var wire 1 , J $end
$var wire 1 - K $end
$var wire 1 . clk $end
$var wire 1 # reset $end
$var reg 1 / Q $end
$upscope $end
$scope module JKFF_ins4 $end
$var wire 1 0 J $end
$var wire 1 1 K $end
$var wire 1 2 clk $end
$var wire 1 # reset $end
$var reg 1 3 Q $end
$upscope $end
$upscope $end
$upscope $end
$enddefinitions $end
$comment Show the parameter values. $end
$dumpall
$end
#0
$dumpvars
03
02
11
10
0/
0.
1-
1,
0+
0*
1)
1(
0'
1&
1%
b0 $
1#
0"
b0 !
$end
#2
0#
1"
#4
1*
b1 !
b1 $
1'
0"
#6
1"
#8
1.
1+
0*
b10 !
b10 $
0'
0"
#10
1"
#12
1*
b11 !
b11 $
1'
0"
#14
1"
#16
12
1/
0.
0+
0*
b100 !
b100 $
0'
0"
#18
1"
#20
1*
b101 !
b101 $
1'
0"
#22
1"
#24
1.
1+
0*
b110 !
b110 $
0'
0"
#26
1"
#28
1*
b111 !
b111 $
1'
0"
#30
1"
#32
13
02
0/
0.
0+
0*
b1000 !
b1000 $
0'
0"
#34
1"
#36
1*
b1001 !
b1001 $
1'
0"
#38
1"
#40
1.
1+
0*
b1010 !
b1010 $
0'
0"
#42
1"
#44
1*
b1011 !
b1011 $
1'
0"
#46
1"
#48
12
1/
0.
0+
0*
b1100 !
b1100 $
0'
0"
#50
1"
#52
1*
b1101 !
b1101 $
1'
0"
#54
1"
#56
1.
1+
0*
b1110 !
b1110 $
0'
0"
#58
1"
#60
1*
b1111 !
b1111 $
1'
0"
#62
1"
#64
03
02
0/
0.
0+
0*
b0 !
b0 $
0'
0"
