TFF.v
module TFF(T,clk,Q,reset);
input T,clk,reset;
output reg Q;

always @(negedge clk, negedge reset)begin
    if(!reset) Q<=0;
    else begin
        if(T==0) Q<=Q;
        else Q<=~Q;
    end
end
endmodule

mod10.v
`include "TFF.v"
module mod10(clk,Q,reset);
input clk,reset;
output [3:0]Q;
wire resetF;
assign resetF = ~(((Q[3]&~Q[2]&Q[1]&~Q[0]))|~reset);
TFF TFF_ins1(1'b1,clk,Q[0],resetF);
TFF TFF_ins2(1'b1,Q[0],Q[1],resetF);
TFF TFF_ins3(1'b1,Q[1],Q[2],resetF);
TFF TFF_ins4(1'b1,Q[2],Q[3],resetF);

endmodule

bcd2.v
`include "mod10.v"
module bcd2(clk,reset,ones,tens);
input clk, reset;
output [3:0] tens, ones;
wire carry;

mod10 ones_counter(clk,ones,reset);

assign carry = (ones == 4'b1001);

mod10 tens_counter(carry,tens,reset);

endmodule

bcd2_tb.v
`include "bcd2.v"
module bcd2_tb();

reg clk, reset;
wire [3:0] ones, tens;

bcd2 bcd2_ins(clk, reset, ones, tens);

initial begin
    $dumpfile("bcd2_tb.vcd");
    $dumpvars(0,bcd2_tb);
end

initial begin
    clk = 0;
    forever #2 clk = ~clk;
end

initial begin
    reset = 0; #2;
    reset = 1; #1000;
    $finish;
end
endmodule

bcd2_tb.vcd
$date
	Wed Nov 05 03:06:48 2025
$end
$version
	Icarus Verilog
$end
$timescale
	1s
$end
$scope module bcd2_tb $end
$var wire 4 ! tens [3:0] $end
$var wire 4 " ones [3:0] $end
$var reg 1 # clk $end
$var reg 1 $ reset $end
$scope module bcd2_ins $end
$var wire 1 # clk $end
$var wire 1 $ reset $end
$var wire 4 % tens [3:0] $end
$var wire 4 & ones [3:0] $end
$var wire 1 ' carry $end
$scope module ones_counter $end
$var wire 1 # clk $end
$var wire 1 $ reset $end
$var wire 1 ( resetF $end
$var wire 4 ) Q [3:0] $end
$scope module TFF_ins1 $end
$var wire 1 * T $end
$var wire 1 # clk $end
$var wire 1 ( reset $end
$var reg 1 + Q $end
$upscope $end
$scope module TFF_ins2 $end
$var wire 1 , T $end
$var wire 1 - clk $end
$var wire 1 ( reset $end
$var reg 1 . Q $end
$upscope $end
$scope module TFF_ins3 $end
$var wire 1 / T $end
$var wire 1 0 clk $end
$var wire 1 ( reset $end
$var reg 1 1 Q $end
$upscope $end
$scope module TFF_ins4 $end
$var wire 1 2 T $end
$var wire 1 3 clk $end
$var wire 1 ( reset $end
$var reg 1 4 Q $end
$upscope $end
$upscope $end
$scope module tens_counter $end
$var wire 1 ' clk $end
$var wire 1 $ reset $end
$var wire 1 5 resetF $end
$var wire 4 6 Q [3:0] $end
$scope module TFF_ins1 $end
$var wire 1 7 T $end
$var wire 1 ' clk $end
$var wire 1 5 reset $end
$var reg 1 8 Q $end
$upscope $end
$scope module TFF_ins2 $end
$var wire 1 9 T $end
$var wire 1 : clk $end
$var wire 1 5 reset $end
$var reg 1 ; Q $end
$upscope $end
$scope module TFF_ins3 $end
$var wire 1 < T $end
$var wire 1 = clk $end
$var wire 1 5 reset $end
$var reg 1 > Q $end
$upscope $end
$scope module TFF_ins4 $end
$var wire 1 ? T $end
$var wire 1 @ clk $end
$var wire 1 5 reset $end
$var reg 1 A Q $end
$upscope $end
$upscope $end
$upscope $end
$upscope $end
$enddefinitions $end
$comment Show the parameter values. $end
$dumpall
$end
#0
$dumpvars
0A
0@
1?
0>
0=
1<
0;
0:
19
08
17
b0 6
05
04
03
12
01
00
1/
0.
0-
1,
0+
1*
b0 )
0(
0'
b0 &
b0 %
0$
0#
b0 "
b0 !
$end
#2
1(
15
1$
1#
#4
1-
b1 "
b1 &
b1 )
1+
0#
#6
1#
#8
10
1.
0-
b10 "
b10 &
b10 )
0+
0#
#10
1#
#12
1-
b11 "
b11 &
b11 )
1+
0#
#14
1#
#16
13
11
00
0.
0-
b100 "
b100 &
b100 )
0+
0#
#18
1#
#20
1-
b101 "
b101 &
b101 )
1+
0#
#22
1#
#24
10
1.
0-
b110 "
b110 &
b110 )
0+
0#
#26
1#
#28
1-
b111 "
b111 &
b111 )
1+
0#
#30
1#
#32
14
03
01
00
0.
0-
b1000 "
b1000 &
b1000 )
0+
0#
#34
1#
#36
1-
1'
b1001 "
b1001 &
b1001 )
1+
0#
#38
1#
#40
04
1(
00
1:
0.
b1 !
b1 %
b1 6
18
0-
0'
b0 "
b0 &
b0 )
0+
0#
#42
1#
#44
1-
b1 "
b1 &
b1 )
1+
0#
#46
1#
#48
10
1.
0-
b10 "
b10 &
b10 )
0+
0#
#50
1#
#52
1-
b11 "
b11 &
b11 )
1+
0#
#54
1#
#56
13
11
00
0.
0-
b100 "
b100 &
b100 )
0+
0#
#58
1#
#60
1-
b101 "
b101 &
b101 )
1+
0#
#62
1#
#64
10
1.
0-
b110 "
b110 &
b110 )
0+
0#
#66
1#
#68
1-
b111 "
b111 &
b111 )
1+
0#
#70
1#
#72
14
03
01
00
0.
0-
b1000 "
b1000 &
b1000 )
0+
0#
#74
1#
#76
1-
1'
b1001 "
b1001 &
b1001 )
1+
0#
#78
1#
#80
1=
04
1;
1(
00
0:
0.
b10 !
b10 %
b10 6
08
0-
0'
b0 "
b0 &
b0 )
0+
0#
#82
1#
#84
1-
b1 "
b1 &
b1 )
1+
0#
#86
1#
#88
10
1.
0-
b10 "
b10 &
b10 )
0+
0#
#90
1#
#92
1-
b11 "
b11 &
b11 )
1+
0#
#94
1#
#96
13
11
00
0.
0-
b100 "
b100 &
b100 )
0+
0#
#98
1#
#100
1-
b101 "
b101 &
b101 )
1+
0#
#102
1#
#104
10
1.
0-
b110 "
b110 &
b110 )
0+
0#
#106
1#
#108
1-
b111 "
b111 &
b111 )
1+
0#
#110
1#
#112
14
03
01
00
0.
0-
b1000 "
b1000 &
b1000 )
0+
0#
#114
1#
#116
1-
1'
b1001 "
b1001 &
b1001 )
1+
0#
#118
1#
#120
04
1(
00
1:
0.
b11 !
b11 %
b11 6
18
0-
0'
b0 "
b0 &
b0 )
0+
0#
#122
1#
#124
1-
b1 "
b1 &
b1 )
1+
0#
#126
1#
#128
10
1.
0-
b10 "
b10 &
b10 )
0+
0#
#130
1#
#132
1-
b11 "
b11 &
b11 )
1+
0#
#134
1#
#136
13
11
00
0.
0-
b100 "
b100 &
b100 )
0+
0#
#138
1#
#140
1-
b101 "
b101 &
b101 )
1+
0#
#142
1#
#144
10
1.
0-
b110 "
b110 &
b110 )
0+
0#
#146
1#
#148
1-
b111 "
b111 &
b111 )
1+
0#
#150
1#
#152
14
03
01
00
0.
0-
b1000 "
b1000 &
b1000 )
0+
0#
#154
1#
#156
1-
1'
b1001 "
b1001 &
b1001 )
1+
0#
#158
1#
#160
1@
1>
0=
04
0;
1(
00
0:
0.
b100 !
b100 %
b100 6
08
0-
0'
b0 "
b0 &
b0 )
0+
0#
#162
1#
#164
1-
b1 "
b1 &
b1 )
1+
0#
#166
1#
#168
10
1.
0-
b10 "
b10 &
b10 )
0+
0#
#170
1#
#172
1-
b11 "
b11 &
b11 )
1+
0#
#174
1#
#176
13
11
00
0.
0-
b100 "
b100 &
b100 )
0+
0#
#178
1#
#180
1-
b101 "
b101 &
b101 )
1+
0#
#182
1#
#184
10
1.
0-
b110 "
b110 &
b110 )
0+
0#
#186
1#
#188
1-
b111 "
b111 &
b111 )
1+
0#
#190
1#
#192
14
03
01
00
0.
0-
b1000 "
b1000 &
b1000 )
0+
0#
#194
1#
#196
1-
1'
b1001 "
b1001 &
b1001 )
1+
0#
#198
1#
#200
04
1(
00
1:
0.
b101 !
b101 %
b101 6
18
0-
0'
b0 "
b0 &
b0 )
0+
0#
#202
1#
#204
1-
b1 "
b1 &
b1 )
1+
0#
#206
1#
#208
10
1.
0-
b10 "
b10 &
b10 )
0+
0#
#210
1#
#212
1-
b11 "
b11 &
b11 )
1+
0#
#214
1#
#216
13
11
00
0.
0-
b100 "
b100 &
b100 )
0+
0#
#218
1#
#220
1-
b101 "
b101 &
b101 )
1+
0#
#222
1#
#224
10
1.
0-
b110 "
b110 &
b110 )
0+
0#
#226
1#
#228
1-
b111 "
b111 &
b111 )
1+
0#
#230
1#
#232
14
03
01
00
0.
0-
b1000 "
b1000 &
b1000 )
0+
0#
#234
1#
#236
1-
1'
b1001 "
b1001 &
b1001 )
1+
0#
#238
1#
#240
1=
04
1;
1(
00
0:
0.
b110 !
b110 %
b110 6
08
0-
0'
b0 "
b0 &
b0 )
0+
0#
#242
1#
#244
1-
b1 "
b1 &
b1 )
1+
0#
#246
1#
#248
10
1.
0-
b10 "
b10 &
b10 )
0+
0#
#250
1#
#252
1-
b11 "
b11 &
b11 )
1+
0#
#254
1#
#256
13
11
00
0.
0-
b100 "
b100 &
b100 )
0+
0#
#258
1#
#260
1-
b101 "
b101 &
b101 )
1+
0#
#262
1#
#264
10
1.
0-
b110 "
b110 &
b110 )
0+
0#
#266
1#
#268
1-
b111 "
b111 &
b111 )
1+
0#
#270
1#
#272
14
03
01
00
0.
0-
b1000 "
b1000 &
b1000 )
0+
0#
#274
1#
#276
1-
1'
b1001 "
b1001 &
b1001 )
1+
0#
#278
1#
#280
04
1(
00
1:
0.
b111 !
b111 %
b111 6
18
0-
0'
b0 "
b0 &
b0 )
0+
0#
#282
1#
#284
1-
b1 "
b1 &
b1 )
1+
0#
#286
1#
#288
10
1.
0-
b10 "
b10 &
b10 )
0+
0#
#290
1#
#292
1-
b11 "
b11 &
b11 )
1+
0#
#294
1#
#296
13
11
00
0.
0-
b100 "
b100 &
b100 )
0+
0#
#298
1#
#300
1-
b101 "
b101 &
b101 )
1+
0#
#302
1#
#304
10
1.
0-
b110 "
b110 &
b110 )
0+
0#
#306
1#
#308
1-
b111 "
b111 &
b111 )
1+
0#
#310
1#
#312
14
03
01
00
0.
0-
b1000 "
b1000 &
b1000 )
0+
0#
#314
1#
#316
1-
1'
b1001 "
b1001 &
b1001 )
1+
0#
#318
1#
#320
1A
0@
0>
0=
04
0;
1(
00
0:
0.
b1000 !
b1000 %
b1000 6
08
0-
0'
b0 "
b0 &
b0 )
0+
0#
#322
1#
#324
1-
b1 "
b1 &
b1 )
1+
0#
#326
1#
#328
10
1.
0-
b10 "
b10 &
b10 )
0+
0#
#330
1#
#332
1-
b11 "
b11 &
b11 )
1+
0#
#334
1#
#336
13
11
00
0.
0-
b100 "
b100 &
b100 )
0+
0#
#338
1#
#340
1-
b101 "
b101 &
b101 )
1+
0#
#342
1#
#344
10
1.
0-
b110 "
b110 &
b110 )
0+
0#
#346
1#
#348
1-
b111 "
b111 &
b111 )
1+
0#
#350
1#
#352
14
03
01
00
0.
0-
b1000 "
b1000 &
b1000 )
0+
0#
#354
1#
#356
1-
1'
b1001 "
b1001 &
b1001 )
1+
0#
#358
1#
#360
04
1(
00
1:
0.
b1001 !
b1001 %
b1001 6
18
0-
0'
b0 "
b0 &
b0 )
0+
0#
#362
1#
#364
1-
b1 "
b1 &
b1 )
1+
0#
#366
1#
#368
10
1.
0-
b10 "
b10 &
b10 )
0+
0#
#370
1#
#372
1-
b11 "
b11 &
b11 )
1+
0#
#374
1#
#376
13
11
00
0.
0-
b100 "
b100 &
b100 )
0+
0#
#378
1#
#380
1-
b101 "
b101 &
b101 )
1+
0#
#382
1#
#384
10
1.
0-
b110 "
b110 &
b110 )
0+
0#
#386
1#
#388
1-
b111 "
b111 &
b111 )
1+
0#
#390
1#
#392
14
03
01
00
0.
0-
b1000 "
b1000 &
b1000 )
0+
0#
#394
1#
#396
1-
1'
b1001 "
b1001 &
b1001 )
1+
0#
#398
1#
#400
0A
15
0=
04
0;
1(
00
0:
0.
b0 !
b0 %
b0 6
08
0-
0'
b0 "
b0 &
b0 )
0+
0#
#402
1#
#404
1-
b1 "
b1 &
b1 )
1+
0#
#406
1#
#408
10
1.
0-
b10 "
b10 &
b10 )
0+
0#
#410
1#
#412
1-
b11 "
b11 &
b11 )
1+
0#
#414
1#
#416
13
11
00
0.
0-
b100 "
b100 &
b100 )
0+
0#
#418
1#
#420
1-
b101 "
b101 &
b101 )
1+
0#
#422
1#
#424
10
1.
0-
b110 "
b110 &
b110 )
0+
0#
#426
1#
#428
1-
b111 "
b111 &
b111 )
1+
0#
#430
1#
#432
14
03
01
00
0.
0-
b1000 "
b1000 &
b1000 )
0+
0#
#434
1#
#436
1-
1'
b1001 "
b1001 &
b1001 )
1+
0#
#438
1#
#440
04
1(
00
1:
0.
b1 !
b1 %
b1 6
18
0-
0'
b0 "
b0 &
b0 )
0+
0#
#442
1#
#444
1-
b1 "
b1 &
b1 )
1+
0#
#446
1#
#448
10
1.
0-
b10 "
b10 &
b10 )
0+
0#
#450
1#
#452
1-
b11 "
b11 &
b11 )
1+
0#
#454
1#
#456
13
11
00
0.
0-
b100 "
b100 &
b100 )
0+
0#
#458
1#
#460
1-
b101 "
b101 &
b101 )
1+
0#
#462
1#
#464
10
1.
0-
b110 "
b110 &
b110 )
0+
0#
#466
1#
#468
1-
b111 "
b111 &
b111 )
1+
0#
#470
1#
#472
14
03
01
00
0.
0-
b1000 "
b1000 &
b1000 )
0+
0#
#474
1#
#476
1-
1'
b1001 "
b1001 &
b1001 )
1+
0#
#478
1#
#480
1=
04
1;
1(
00
0:
0.
b10 !
b10 %
b10 6
08
0-
0'
b0 "
b0 &
b0 )
0+
0#
#482
1#
#484
1-
b1 "
b1 &
b1 )
1+
0#
#486
1#
#488
10
1.
0-
b10 "
b10 &
b10 )
0+
0#
#490
1#
#492
1-
b11 "
b11 &
b11 )
1+
0#
#494
1#
#496
13
11
00
0.
0-
b100 "
b100 &
b100 )
0+
0#
#498
1#
#500
1-
b101 "
b101 &
b101 )
1+
0#
#502
1#
#504
10
1.
0-
b110 "
b110 &
b110 )
0+
0#
#506
1#
#508
1-
b111 "
b111 &
b111 )
1+
0#
#510
1#
#512
14
03
01
00
0.
0-
b1000 "
b1000 &
b1000 )
0+
0#
#514
1#
#516
1-
1'
b1001 "
b1001 &
b1001 )
1+
0#
#518
1#
#520
04
1(
00
1:
0.
b11 !
b11 %
b11 6
18
0-
0'
b0 "
b0 &
b0 )
0+
0#
#522
1#
#524
1-
b1 "
b1 &
b1 )
1+
0#
#526
1#
#528
10
1.
0-
b10 "
b10 &
b10 )
0+
0#
#530
1#
#532
1-
b11 "
b11 &
b11 )
1+
0#
#534
1#
#536
13
11
00
0.
0-
b100 "
b100 &
b100 )
0+
0#
#538
1#
#540
1-
b101 "
b101 &
b101 )
1+
0#
#542
1#
#544
10
1.
0-
b110 "
b110 &
b110 )
0+
0#
#546
1#
#548
1-
b111 "
b111 &
b111 )
1+
0#
#550
1#
#552
14
03
01
00
0.
0-
b1000 "
b1000 &
b1000 )
0+
0#
#554
1#
#556
1-
1'
b1001 "
b1001 &
b1001 )
1+
0#
#558
1#
#560
1@
1>
0=
04
0;
1(
00
0:
0.
b100 !
b100 %
b100 6
08
0-
0'
b0 "
b0 &
b0 )
0+
0#
#562
1#
#564
1-
b1 "
b1 &
b1 )
1+
0#
#566
1#
#568
10
1.
0-
b10 "
b10 &
b10 )
0+
0#
#570
1#
#572
1-
b11 "
b11 &
b11 )
1+
0#
#574
1#
#576
13
11
00
0.
0-
b100 "
b100 &
b100 )
0+
0#
#578
1#
#580
1-
b101 "
b101 &
b101 )
1+
0#
#582
1#
#584
10
1.
0-
b110 "
b110 &
b110 )
0+
0#
#586
1#
#588
1-
b111 "
b111 &
b111 )
1+
0#
#590
1#
#592
14
03
01
00
0.
0-
b1000 "
b1000 &
b1000 )
0+
0#
#594
1#
#596
1-
1'
b1001 "
b1001 &
b1001 )
1+
0#
#598
1#
#600
04
1(
00
1:
0.
b101 !
b101 %
b101 6
18
0-
0'
b0 "
b0 &
b0 )
0+
0#
#602
1#
#604
1-
b1 "
b1 &
b1 )
1+
0#
#606
1#
#608
10
1.
0-
b10 "
b10 &
b10 )
0+
0#
#610
1#
#612
1-
b11 "
b11 &
b11 )
1+
0#
#614
1#
#616
13
11
00
0.
0-
b100 "
b100 &
b100 )
0+
0#
#618
1#
#620
1-
b101 "
b101 &
b101 )
1+
0#
#622
1#
#624
10
1.
0-
b110 "
b110 &
b110 )
0+
0#
#626
1#
#628
1-
b111 "
b111 &
b111 )
1+
0#
#630
1#
#632
14
03
01
00
0.
0-
b1000 "
b1000 &
b1000 )
0+
0#
#634
1#
#636
1-
1'
b1001 "
b1001 &
b1001 )
1+
0#
#638
1#
#640
1=
04
1;
1(
00
0:
0.
b110 !
b110 %
b110 6
08
0-
0'
b0 "
b0 &
b0 )
0+
0#
#642
1#
#644
1-
b1 "
b1 &
b1 )
1+
0#
#646
1#
#648
10
1.
0-
b10 "
b10 &
b10 )
0+
0#
#650
1#
#652
1-
b11 "
b11 &
b11 )
1+
0#
#654
1#
#656
13
11
00
0.
0-
b100 "
b100 &
b100 )
0+
0#
#658
1#
#660
1-
b101 "
b101 &
b101 )
1+
0#
#662
1#
#664
10
1.
0-
b110 "
b110 &
b110 )
0+
0#
#666
1#
#668
1-
b111 "
b111 &
b111 )
1+
0#
#670
1#
#672
14
03
01
00
0.
0-
b1000 "
b1000 &
b1000 )
0+
0#
#674
1#
#676
1-
1'
b1001 "
b1001 &
b1001 )
1+
0#
#678
1#
#680
04
1(
00
1:
0.
b111 !
b111 %
b111 6
18
0-
0'
b0 "
b0 &
b0 )
0+
0#
#682
1#
#684
1-
b1 "
b1 &
b1 )
1+
0#
#686
1#
#688
10
1.
0-
b10 "
b10 &
b10 )
0+
0#
#690
1#
#692
1-
b11 "
b11 &
b11 )
1+
0#
#694
1#
#696
13
11
00
0.
0-
b100 "
b100 &
b100 )
0+
0#
#698
1#
#700
1-
b101 "
b101 &
b101 )
1+
0#
#702
1#
#704
10
1.
0-
b110 "
b110 &
b110 )
0+
0#
#706
1#
#708
1-
b111 "
b111 &
b111 )
1+
0#
#710
1#
#712
14
03
01
00
0.
0-
b1000 "
b1000 &
b1000 )
0+
0#
#714
1#
#716
1-
1'
b1001 "
b1001 &
b1001 )
1+
0#
#718
1#
#720
1A
0@
0>
0=
04
0;
1(
00
0:
0.
b1000 !
b1000 %
b1000 6
08
0-
0'
b0 "
b0 &
b0 )
0+
0#
#722
1#
#724
1-
b1 "
b1 &
b1 )
1+
0#
#726
1#
#728
10
1.
0-
b10 "
b10 &
b10 )
0+
0#
#730
1#
#732
1-
b11 "
b11 &
b11 )
1+
0#
#734
1#
#736
13
11
00
0.
0-
b100 "
b100 &
b100 )
0+
0#
#738
1#
#740
1-
b101 "
b101 &
b101 )
1+
0#
#742
1#
#744
10
1.
0-
b110 "
b110 &
b110 )
0+
0#
#746
1#
#748
1-
b111 "
b111 &
b111 )
1+
0#
#750
1#
#752
14
03
01
00
0.
0-
b1000 "
b1000 &
b1000 )
0+
0#
#754
1#
#756
1-
1'
b1001 "
b1001 &
b1001 )
1+
0#
#758
1#
#760
04
1(
00
1:
0.
b1001 !
b1001 %
b1001 6
18
0-
0'
b0 "
b0 &
b0 )
0+
0#
#762
1#
#764
1-
b1 "
b1 &
b1 )
1+
0#
#766
1#
#768
10
1.
0-
b10 "
b10 &
b10 )
0+
0#
#770
1#
#772
1-
b11 "
b11 &
b11 )
1+
0#
#774
1#
#776
13
11
00
0.
0-
b100 "
b100 &
b100 )
0+
0#
#778
1#
#780
1-
b101 "
b101 &
b101 )
1+
0#
#782
1#
#784
10
1.
0-
b110 "
b110 &
b110 )
0+
0#
#786
1#
#788
1-
b111 "
b111 &
b111 )
1+
0#
#790
1#
#792
14
03
01
00
0.
0-
b1000 "
b1000 &
b1000 )
0+
0#
#794
1#
#796
1-
1'
b1001 "
b1001 &
b1001 )
1+
0#
#798
1#
#800
0A
15
0=
04
0;
1(
00
0:
0.
b0 !
b0 %
b0 6
08
0-
0'
b0 "
b0 &
b0 )
0+
0#
#802
1#
#804
1-
b1 "
b1 &
b1 )
1+
0#
#806
1#
#808
10
1.
0-
b10 "
b10 &
b10 )
0+
0#
#810
1#
#812
1-
b11 "
b11 &
b11 )
1+
0#
#814
1#
#816
13
11
00
0.
0-
b100 "
b100 &
b100 )
0+
0#
#818
1#
#820
1-
b101 "
b101 &
b101 )
1+
0#
#822
1#
#824
10
1.
0-
b110 "
b110 &
b110 )
0+
0#
#826
1#
#828
1-
b111 "
b111 &
b111 )
1+
0#
#830
1#
#832
14
03
01
00
0.
0-
b1000 "
b1000 &
b1000 )
0+
0#
#834
1#
#836
1-
1'
b1001 "
b1001 &
b1001 )
1+
0#
#838
1#
#840
04
1(
00
1:
0.
b1 !
b1 %
b1 6
18
0-
0'
b0 "
b0 &
b0 )
0+
0#
#842
1#
#844
1-
b1 "
b1 &
b1 )
1+
0#
#846
1#
#848
10
1.
0-
b10 "
b10 &
b10 )
0+
0#
#850
1#
#852
1-
b11 "
b11 &
b11 )
1+
0#
#854
1#
#856
13
11
00
0.
0-
b100 "
b100 &
b100 )
0+
0#
#858
1#
#860
1-
b101 "
b101 &
b101 )
1+
0#
#862
1#
#864
10
1.
0-
b110 "
b110 &
b110 )
0+
0#
#866
1#
#868
1-
b111 "
b111 &
b111 )
1+
0#
#870
1#
#872
14
03
01
00
0.
0-
b1000 "
b1000 &
b1000 )
0+
0#
#874
1#
#876
1-
1'
b1001 "
b1001 &
b1001 )
1+
0#
#878
1#
#880
1=
04
1;
1(
00
0:
0.
b10 !
b10 %
b10 6
08
0-
0'
b0 "
b0 &
b0 )
0+
0#
#882
1#
#884
1-
b1 "
b1 &
b1 )
1+
0#
#886
1#
#888
10
1.
0-
b10 "
b10 &
b10 )
0+
0#
#890
1#
#892
1-
b11 "
b11 &
b11 )
1+
0#
#894
1#
#896
13
11
00
0.
0-
b100 "
b100 &
b100 )
0+
0#
#898
1#
#900
1-
b101 "
b101 &
b101 )
1+
0#
#902
1#
#904
10
1.
0-
b110 "
b110 &
b110 )
0+
0#
#906
1#
#908
1-
b111 "
b111 &
b111 )
1+
0#
#910
1#
#912
14
03
01
00
0.
0-
b1000 "
b1000 &
b1000 )
0+
0#
#914
1#
#916
1-
1'
b1001 "
b1001 &
b1001 )
1+
0#
#918
1#
#920
04
1(
00
1:
0.
b11 !
b11 %
b11 6
18
0-
0'
b0 "
b0 &
b0 )
0+
0#
#922
1#
#924
1-
b1 "
b1 &
b1 )
1+
0#
#926
1#
#928
10
1.
0-
b10 "
b10 &
b10 )
0+
0#
#930
1#
#932
1-
b11 "
b11 &
b11 )
1+
0#
#934
1#
#936
13
11
00
0.
0-
b100 "
b100 &
b100 )
0+
0#
#938
1#
#940
1-
b101 "
b101 &
b101 )
1+
0#
#942
1#
#944
10
1.
0-
b110 "
b110 &
b110 )
0+
0#
#946
1#
#948
1-
b111 "
b111 &
b111 )
1+
0#
#950
1#
#952
14
03
01
00
0.
0-
b1000 "
b1000 &
b1000 )
0+
0#
#954
1#
#956
1-
1'
b1001 "
b1001 &
b1001 )
1+
0#
#958
1#
#960
1@
1>
0=
04
0;
1(
00
0:
0.
b100 !
b100 %
b100 6
08
0-
0'
b0 "
b0 &
b0 )
0+
0#
#962
1#
#964
1-
b1 "
b1 &
b1 )
1+
0#
#966
1#
#968
10
1.
0-
b10 "
b10 &
b10 )
0+
0#
#970
1#
#972
1-
b11 "
b11 &
b11 )
1+
0#
#974
1#
#976
13
11
00
0.
0-
b100 "
b100 &
b100 )
0+
0#
#978
1#
#980
1-
b101 "
b101 &
b101 )
1+
0#
#982
1#
#984
10
1.
0-
b110 "
b110 &
b110 )
0+
0#
#986
1#
#988
1-
b111 "
b111 &
b111 )
1+
0#
#990
1#
#992
14
03
01
00
0.
0-
b1000 "
b1000 &
b1000 )
0+
0#
#994
1#
#996
1-
1'
b1001 "
b1001 &
b1001 )
1+
0#
#998
1#
#1000
04
1(
00
1:
0.
b101 !
b101 %
b101 6
18
0-
0'
b0 "
b0 &
b0 )
0+
0#
