dec2to4.v
module dec2to4(w,en,y);
input [1:0] w;
input en;
output reg[0:3] y;

always @(*)begin
    if(en==0) y = 4'b0000;
    else begin
        if(w==0) y = 4'b1000;
        else if(w==1) y = 4'b0100;
        else if(w==2) y = 4'b0010;
        else if(w==3) y = 4'b0001;
    end
end
endmodule

dec3to8.v
`include "dec2to4.v"

module dec3to8(w,en,y);

input [2:0] w;
input en;
output [0:7]y;

dec2to4 dec2to4_1(w[1:0],(~w[2]&en),y[0:3]);
dec2to4 dec2to4_2(w[1:0],(w[2]&en),y[4:7]);

endmodule

dec3to8_tb.v
`include "dec3to8.v"
`timescale 1ns/1ns

module dec3to8_tb();

reg [2:0] w;
reg en;
wire [0:7] y;

dec3to8 dec3to8_ins(w,en,y);

initial begin
    $dumpfile("dec3to8_tb.vcd");
    $dumpvars(0,dec3to8_tb);
end

initial begin
    en = 0; w= 0; #2;
    en = 1;
    w = 0; #2;
    w = 1; #2; 
    w = 2; #2;
    w = 3; #2;
    w = 4; #2;
    w = 5; #2;
    w = 6; #2;
    w = 7; #2;
end
endmodule

dec3to8_tb.vcd
$date
	Wed Nov 05 10:49:15 2025
$end
$version
	Icarus Verilog
$end
$timescale
	1ns
$end
$scope module dec3to8_tb $end
$var wire 8 ! y [0:7] $end
$var reg 1 " en $end
$var reg 3 # w [2:0] $end
$scope module dec3to8_ins $end
$var wire 1 " en $end
$var wire 3 $ w [2:0] $end
$var wire 8 % y [0:7] $end
$scope module dec2to4_1 $end
$var wire 1 & en $end
$var wire 2 ' w [1:0] $end
$var reg 4 ( y [0:3] $end
$upscope $end
$scope module dec2to4_2 $end
$var wire 1 ) en $end
$var wire 2 * w [1:0] $end
$var reg 4 + y [0:3] $end
$upscope $end
$upscope $end
$upscope $end
$enddefinitions $end
$comment Show the parameter values. $end
$dumpall
$end
#0
$dumpvars
b0 +
b0 *
0)
b0 (
b0 '
0&
b0 %
b0 $
b0 #
0"
b0 !
$end
#2
b10000000 !
b10000000 %
b1000 (
1&
1"
#4
b1000000 !
b1000000 %
b100 (
b1 '
b1 *
b1 #
b1 $
#6
b100000 !
b100000 %
b10 (
b10 '
b10 *
b10 #
b10 $
#8
b10000 !
b10000 %
b1 (
b11 '
b11 *
b11 #
b11 $
#10
0&
b0 (
b1000 !
b1000 %
b1000 +
1)
b0 '
b0 *
b100 #
b100 $
#12
b100 !
b100 %
b100 +
b1 '
b1 *
b101 #
b101 $
#14
b10 !
b10 %
b10 +
b10 '
b10 *
b110 #
b110 $
#16
b1 !
b1 %
b1 +
b11 '
b11 *
b111 #
b111 $
