JKFF_active_low.v
module JKFF_active_low(J,K,clk,Q,reset);
input J,K,clk,reset;
output reg Q;

always @(posedge clk, negedge reset)begin
    if(!reset) Q<=0;
    else begin
        if(J==0&&K==0) Q<=Q;
        else if(J==0&&K==1) Q<=0;
        else if(J==1&&K==0) Q<=1;
        else if(J==1&&K==1) Q<=~Q;
    end
end
endmodule

JKFF_active_low_tb.v
`include "JKFF_active_low.v"
`timescale 1ns/1ns

module JKFF_active_low_tb();

reg J,K,clk,reset;
wire Q;

JKFF_active_low JKFF_active_low_ins(J,K,clk,Q,reset);

initial begin
    $dumpfile("JKFF_active_low_tb.vcd");
    $dumpvars(0,JKFF_active_low_tb);
end

initial begin
    clk = 0;
    forever #2 clk = ~clk;
end

initial begin
    reset = 0; J = 0; K = 0; #2;
    reset = 0; J = 0; K = 1; #2;
    reset = 0; J = 1; K = 0; #2;
    reset = 0; J = 1; K = 1; #2;

    reset = 1; J = 0; K = 0; #2;
    reset = 1; J = 0; K = 1; #2;
    reset = 1; J = 1; K = 0; #2;
    reset = 1; J = 1; K = 1; #2;

    $finish;
end
endmodule

JKFF_active_low_tb.vcd
$date
	Tue Nov 04 13:31:56 2025
$end
$version
	Icarus Verilog
$end
$timescale
	1ns
$end
$scope module JKFF_active_low_tb $end
$var wire 1 ! Q $end
$var reg 1 " J $end
$var reg 1 # K $end
$var reg 1 $ clk $end
$var reg 1 % reset $end
$scope module JKFF_active_low_ins $end
$var wire 1 " J $end
$var wire 1 # K $end
$var wire 1 $ clk $end
$var wire 1 % reset $end
$var reg 1 ! Q $end
$upscope $end
$upscope $end
$enddefinitions $end
$comment Show the parameter values. $end
$dumpall
$end
#0
$dumpvars
0%
0$
0#
0"
0!
$end
#2
1#
1$
#4
0#
1"
0$
#6
1#
1$
#8
0#
0"
1%
0$
#10
1#
1$
#12
0#
1"
0$
#14
1!
1#
1$
