johnson5bit.v
module johnson5bit(clk,reset,Q);
input clk,reset;
output reg [4:0] Q;

always @(posedge clk, posedge reset) begin
    if(reset) Q<= 5'b00000;
    else begin
        Q[4]<=~Q[0];
        for(integer i = 3; i>=0; i--)begin
            Q[i]<=Q[i+1];
        end
    end
end
endmodule

johnson5bit_tb.v
`include "johnson5bit.v"
module johnson5bit_tb();

reg clk, reset;
wire [4:0] Q;

johnson5bit johnson5bit(clk, reset, Q);


initial begin
    $dumpfile("johnson5bit_tb.vcd");
    $dumpvars(0,johnson5bit_tb);
end

initial begin
    clk = 0;
    forever #2 clk = ~clk;
end

initial begin
    reset = 1; #2;
    reset = 0; #40;
    $finish;
end
endmodule

johnson5bit_tb.vcd
$date
	Tue Nov 04 13:55:19 2025
$end
$version
	Icarus Verilog
$end
$timescale
	1s
$end
$scope module johnson5bit_tb $end
$var wire 5 ! Q [4:0] $end
$var reg 1 " clk $end
$var reg 1 # reset $end
$scope module johnson5bit $end
$var wire 1 " clk $end
$var wire 1 # reset $end
$var reg 5 $ Q [4:0] $end
$scope begin $ivl_for_loop0 $end
$var integer 32 % i [31:0] $end
$upscope $end
$upscope $end
$upscope $end
$enddefinitions $end
$comment Show the parameter values. $end
$dumpall
$end
#0
$dumpvars
bx %
b0 $
1#
0"
b0 !
$end
#2
b10000 !
b10000 $
b11111111111111111111111111111111 %
0#
1"
#4
0"
#6
b11000 !
b11000 $
b11111111111111111111111111111111 %
1"
#8
0"
#10
b11100 !
b11100 $
b11111111111111111111111111111111 %
1"
#12
0"
#14
b11110 !
b11110 $
b11111111111111111111111111111111 %
1"
#16
0"
#18
b11111 !
b11111 $
b11111111111111111111111111111111 %
1"
#20
0"
#22
b1111 !
b1111 $
b11111111111111111111111111111111 %
1"
#24
0"
#26
b111 !
b111 $
b11111111111111111111111111111111 %
1"
#28
0"
#30
b11 !
b11 $
b11111111111111111111111111111111 %
1"
#32
0"
#34
b1 !
b1 $
b11111111111111111111111111111111 %
1"
#36
0"
#38
b0 !
b0 $
b11111111111111111111111111111111 %
1"
#40
0"
#42
b10000 !
b10000 $
b11111111111111111111111111111111 %
1"
