TFF.v
module TFF(T,clk,Q,reset);
input T,clk,reset;
output reg Q;

always @(negedge clk, negedge reset)begin
    if(!reset) Q<=0;
    else begin
        if(T==0) Q<=Q;
        else Q<=~Q;
    end
end
endmodule

L10Q3.v
`include "TFF.v"
module L10Q3(clk,reset,A,B,C,out);

input clk,reset;
output A,B,C;
output [2:0] out;

wire Ta,Tb,Tc;

assign Ta = B;
assign Tb = C;
assign Tc = (~C)|(A&B);

TFF TFF1(Ta,clk,A,reset);
TFF TFF2(Tb,clk,B,reset);
TFF TFF3(Tc,clk,C,reset);

assign out = {A,B,C};
endmodule

L10Q3_tb.v
`include "L10Q3.v"
`timescale 1ns/1ns
module L10Q3_tb();

reg clk, reset;
wire A,B,C;
wire [2:0] out;

L10Q3 L10Q3_ins(clk,reset,A,B,C,out);

initial begin
    $dumpfile("L10Q3_tb.vcd");
    $dumpvars(0,L10Q3_tb);
end

initial begin
    clk = 0;
    forever #2 clk = ~clk;
end

initial begin
    reset = 0; #2;
    reset = 1; #40;
    $finish;
end
endmodule

L10Q3_tb.vcd
$date
	Wed Nov 05 00:00:26 2025
$end
$version
	Icarus Verilog
$end
$timescale
	1ns
$end
$scope module L10Q3_tb $end
$var wire 3 ! out [2:0] $end
$var wire 1 " C $end
$var wire 1 # B $end
$var wire 1 $ A $end
$var reg 1 % clk $end
$var reg 1 & reset $end
$scope module L10Q3_ins $end
$var wire 1 ' Ta $end
$var wire 1 ( Tb $end
$var wire 1 ) Tc $end
$var wire 1 % clk $end
$var wire 1 & reset $end
$var wire 3 * out [2:0] $end
$var wire 1 " C $end
$var wire 1 # B $end
$var wire 1 $ A $end
$scope module TFF1 $end
$var wire 1 ' T $end
$var wire 1 % clk $end
$var wire 1 & reset $end
$var reg 1 $ Q $end
$upscope $end
$scope module TFF2 $end
$var wire 1 ( T $end
$var wire 1 % clk $end
$var wire 1 & reset $end
$var reg 1 # Q $end
$upscope $end
$scope module TFF3 $end
$var wire 1 ) T $end
$var wire 1 % clk $end
$var wire 1 & reset $end
$var reg 1 " Q $end
$upscope $end
$upscope $end
$upscope $end
$enddefinitions $end
$comment Show the parameter values. $end
$dumpall
$end
#0
$dumpvars
b0 *
1)
0(
0'
0&
0%
0$
0#
0"
b0 !
$end
#2
1&
1%
#4
0)
b1 !
b1 *
1(
1"
0%
#6
1%
#8
b11 !
b11 *
1'
1#
0%
#10
1%
#12
0'
0#
b101 !
b101 *
1$
0%
#14
1%
#16
1)
b111 !
b111 *
1'
1#
0%
#18
1%
#20
0(
0"
0'
0#
b0 !
b0 *
0$
0%
#22
1%
#24
0)
b1 !
b1 *
1(
1"
0%
#26
1%
#28
b11 !
b11 *
1'
1#
0%
#30
1%
#32
1$
b101 !
b101 *
0'
0#
0%
#34
1%
#36
1)
b111 !
b111 *
1'
1#
0%
#38
1%
#40
0$
0'
0#
b0 !
b0 *
0(
0"
0%
