SRFF.v
module SRFF(S,R,clk,Q,reset);

input S,R,clk,reset;
output reg Q;

always @(posedge clk, posedge reset) begin
    if(reset) Q<=0;
    else begin
        if(S==0&&R==0) Q<=Q;
        else if(S==0&&R==1) Q<=0;
        else if(S==1&&R==0) Q<=1;
        else if(S==1&&R==1) Q<=1'bx;
    end
end
endmodule

L9A2.v
`include "SRFF.v"

module L9A2(x,clk,reset,A,B);
input x,clk,reset;
output A,B;

wire Sa,Ra,Sb,Rb;

assign Sa = (~x&~A&~B)|(x&B);
assign Ra = (~x&A&~B);
assign Sb = ~A|x;
assign Rb = (~x&A);

SRFF SRFF_insa(Sa,Ra,clk,A,reset);
SRFF SRFF_insb(Sb,Rb,clk,B,reset);

endmodule

L9A2_tb.v
`include "L9A2.v"
`timescale 1ns/1ns
module L9A2_tb();

reg x,clk,reset;
wire A,B;

L9A2 L9A2_ins(x,clk,reset,A,B);

initial begin
    $dumpfile("L9A2_tb.vcd");
    $dumpvars(0,L9A2_tb);
end

initial begin
    clk = 0;
    forever #2 clk = ~clk;
end

initial begin
    reset =1;
    x=0; #2;
    reset =0;
    x=1; #2;
    x=0; #2;
    x=1; #2;
    x=0; #2;
    x=1; #2;
    x=0; #2;
    x=1; #2;
    x=0; #2;
    x=1; #2;
    x=0; #2;
   $finish; 
end
endmodule

L9A2_tb.vcd
$date
	Tue Nov 04 16:13:09 2025
$end
$version
	Icarus Verilog
$end
$timescale
	1ns
$end
$scope module L9A2_tb $end
$var wire 1 ! B $end
$var wire 1 " A $end
$var reg 1 # clk $end
$var reg 1 $ reset $end
$var reg 1 % x $end
$scope module L9A2_ins $end
$var wire 1 & Ra $end
$var wire 1 ' Rb $end
$var wire 1 ( Sa $end
$var wire 1 ) Sb $end
$var wire 1 # clk $end
$var wire 1 $ reset $end
$var wire 1 % x $end
$var wire 1 ! B $end
$var wire 1 " A $end
$scope module SRFF_insa $end
$var wire 1 & R $end
$var wire 1 ( S $end
$var wire 1 # clk $end
$var wire 1 $ reset $end
$var reg 1 " Q $end
$upscope $end
$scope module SRFF_insb $end
$var wire 1 ' R $end
$var wire 1 ) S $end
$var wire 1 # clk $end
$var wire 1 $ reset $end
$var reg 1 ! Q $end
$upscope $end
$upscope $end
$upscope $end
$enddefinitions $end
$comment Show the parameter values. $end
$dumpall
$end
#0
$dumpvars
1)
1(
0'
0&
0%
1$
0#
0"
0!
$end
#2
1!
1"
1(
1%
0$
1#
#4
0(
1'
0)
0%
0#
#6
0!
0(
0'
1)
1%
1#
#8
1&
1'
0)
0%
0#
#10
0"
0&
0'
1)
1%
1#
#12
1(
0%
0#
#14
1"
1!
1(
1%
1#
#16
0(
1'
0)
0%
0#
#18
0!
0(
0'
1)
1%
1#
#20
1&
1'
0)
0%
0#
#22
1(
1)
0&
0'
0"
1#
