JKFF.v
module JKFF(J,K,clk,Q,reset);

input J,K,clk,reset;
output reg Q;

always @(negedge clk,posedge reset)begin
    if(reset) Q<=0;
    else begin
        if(J==0&&K==0) Q<=Q;
        else if(J==0&&K==1) Q<=0;
        else if(J==1&&K==0) Q<=1;
        else if(J==1&&K==1) Q<=~Q;
    end
end
endmodule

L9Q1.v
`include "JKFF.v"
module L9Q1(E,x,clk,reset,Qa,Qb);
input E,x,clk, reset;
output Qa, Qb;
wire Ja, Ka, Jb, Kb;

assign Ja = (E&x&Qb)|(E&~x&~Qb);
assign Ka = (E&x&Qb)|(E&~x&~Qb);
assign Jb = E;
assign Kb = E;

JKFF JKFFa(Ja,Ka,clk,Qa,reset);
JKFF JKFFb(Jb,Kb,clk,Qb,reset);

endmodule

L9Q1_tb.v
`include "L9Q1.v"
`timescale 1ns/1ns

module L9Q1_tb();

reg E,x,clk, reset;
wire Qa, Qb;

L9Q1 L9Q1_ins(E,x,clk,reset,Qa,Qb);

initial begin
    $dumpfile("L9Q1_tb.vcd");
    $dumpvars(0,L9Q1_tb);
end

initial begin
    clk = 0;
    forever #2 clk = ~clk;
end

initial begin
    reset = 1; E = 0; x = 0; #3;
    reset = 0;
    E = 0; x = 0; #5;
    E = 0; x = 1; #5;
    E = 1; x = 0; #5;
    E = 1; x = 1; #5;
    $finish;
end

endmodule

L9Q1_tb.vcd
$date
	Tue Nov 04 15:24:52 2025
$end
$version
	Icarus Verilog
$end
$timescale
	1ns
$end
$scope module L9Q1_tb $end
$var wire 1 ! Qb $end
$var wire 1 " Qa $end
$var reg 1 # E $end
$var reg 1 $ clk $end
$var reg 1 % reset $end
$var reg 1 & x $end
$scope module L9Q1_ins $end
$var wire 1 # E $end
$var wire 1 ' Ja $end
$var wire 1 ( Jb $end
$var wire 1 ) Ka $end
$var wire 1 * Kb $end
$var wire 1 $ clk $end
$var wire 1 % reset $end
$var wire 1 & x $end
$var wire 1 ! Qb $end
$var wire 1 " Qa $end
$scope module JKFFa $end
$var wire 1 ' J $end
$var wire 1 ) K $end
$var wire 1 $ clk $end
$var wire 1 % reset $end
$var reg 1 " Q $end
$upscope $end
$scope module JKFFb $end
$var wire 1 ( J $end
$var wire 1 * K $end
$var wire 1 $ clk $end
$var wire 1 % reset $end
$var reg 1 ! Q $end
$upscope $end
$upscope $end
$upscope $end
$enddefinitions $end
$comment Show the parameter values. $end
$dumpall
$end
#0
$dumpvars
0*
0)
0(
0'
0&
1%
0$
0#
x"
x!
$end
#2
0"
0!
1$
#3
0%
#4
0$
#6
1$
#8
0$
1&
#10
1$
#12
0$
#13
1'
1)
0&
1(
1*
1#
#14
0)
0'
1!
1"
1$
#16
0$
#18
0!
0'
0)
1$
1&
#20
0$
#22
1)
1'
1!
1$
