TFF.v
module TFF(T,clk,Q,reset);
input T,clk,reset;
output reg Q;

always @(negedge clk, negedge reset)begin
    if(!reset) Q<=0;
    else begin
        if(T==0) Q<=Q;
        else Q<=~Q;
    end
end
endmodule

L9Q2.v
`include "TFF.v"
module L9Q2(x,clk,reset,A,B);
input x,clk, reset;
output A,B;
wire Ta,Tb;

assign Ta = (B&~x)|(~A&B);
assign Tb = (~A&B&x)|(~B&~x)|(A&~x);

TFF TFF_insa(Ta,clk,A,reset);
TFF TFF_insb(Tb,clk,B,reset);
endmodule

L9Q2_tb.v
`include "L9Q2.v"
`timescale 1ns/1ns

module L9Q2_tb();
reg clk,x,reset;
wire A,B;


L9Q2 L9Q2_ins(x,clk,reset,A,B);


initial begin
    $dumpfile("L9Q2_tb.vcd");
    $dumpvars(0,L9Q2_tb);
end

initial begin
    clk = 0; 
    forever #2 clk = ~clk;
end

initial begin
    reset = 0; x = 0; #2;
    reset = 0; x = 1; #2;

    reset = 1; 
    x = 0; #2;
    x = 1; #2;
    x = 1; #2;
    x = 0; #2;
    x = 1; #2;
    x = 1; #2;
    x = 1; #2;
    x = 0; #2;
    $finish;
end
endmodule

L9Q2_tb.vcd
$date
	Tue Nov 04 15:41:26 2025
$end
$version
	Icarus Verilog
$end
$timescale
	1ns
$end
$scope module L9Q2_tb $end
$var wire 1 ! B $end
$var wire 1 " A $end
$var reg 1 # clk $end
$var reg 1 $ reset $end
$var reg 1 % x $end
$scope module L9Q2_ins $end
$var wire 1 & Ta $end
$var wire 1 ' Tb $end
$var wire 1 # clk $end
$var wire 1 $ reset $end
$var wire 1 % x $end
$var wire 1 ! B $end
$var wire 1 " A $end
$scope module TFF_insa $end
$var wire 1 & T $end
$var wire 1 # clk $end
$var wire 1 $ reset $end
$var reg 1 " Q $end
$upscope $end
$scope module TFF_insb $end
$var wire 1 ' T $end
$var wire 1 # clk $end
$var wire 1 $ reset $end
$var reg 1 ! Q $end
$upscope $end
$upscope $end
$upscope $end
$enddefinitions $end
$comment Show the parameter values. $end
$dumpall
$end
#0
$dumpvars
1'
0&
0%
0$
0#
0"
0!
$end
#2
0'
1%
1#
#4
1'
0%
1$
0#
#6
0'
1%
1#
#8
0#
#10
1'
0%
1#
#12
1&
1!
1'
1%
0#
#14
1#
#16
0'
0&
1"
0!
0#
#18
1'
0%
1#
#20
1&
1!
0#
