TFF.v
module TFF(T,clk,Q,reset);
input T,clk,reset;
output reg Q;

always @(negedge clk, negedge reset)begin
    if(!reset) Q<=0;
    else begin
        if(T==0) Q<=Q;
        else Q<=~Q;
    end
end
endmodule

mod10.v
`include "TFF.v"
module mod10(clk,Q,reset);
input clk,reset;
output [3:0]Q;
wire resetF;
assign resetF = ~(((Q[3]&~Q[2]&Q[1]&~Q[0]))|~reset);
TFF TFF_ins1(1'b1,clk,Q[0],resetF);
TFF TFF_ins2(1'b1,Q[0],Q[1],resetF);
TFF TFF_ins3(1'b1,Q[1],Q[2],resetF);
TFF TFF_ins4(1'b1,Q[2],Q[3],resetF);

endmodule

mod10_tb.v
`include "mod10.v"
module mod10_tb();
reg clk, reset;
wire [3:0] Q;

mod10 mod10_ins(clk,Q,reset);

initial begin
    $dumpfile("mod10_tb.vcd");
    $dumpvars(0,mod10_tb);
end

initial begin
    clk = 0;
    forever #2 clk = ~clk;
end

initial begin
    reset = 0; #2;
    reset = 1; #80;
    $finish;
end

endmodule

mod10_tb.vcd
$date
	Wed Nov 05 02:54:40 2025
$end
$version
	Icarus Verilog
$end
$timescale
	1s
$end
$scope module mod10_tb $end
$var wire 4 ! Q [3:0] $end
$var reg 1 " clk $end
$var reg 1 # reset $end
$scope module mod10_ins $end
$var wire 1 " clk $end
$var wire 1 # reset $end
$var wire 1 $ resetF $end
$var wire 4 % Q [3:0] $end
$scope module TFF_ins1 $end
$var wire 1 & T $end
$var wire 1 " clk $end
$var wire 1 $ reset $end
$var reg 1 ' Q $end
$upscope $end
$scope module TFF_ins2 $end
$var wire 1 ( T $end
$var wire 1 ) clk $end
$var wire 1 $ reset $end
$var reg 1 * Q $end
$upscope $end
$scope module TFF_ins3 $end
$var wire 1 + T $end
$var wire 1 , clk $end
$var wire 1 $ reset $end
$var reg 1 - Q $end
$upscope $end
$scope module TFF_ins4 $end
$var wire 1 . T $end
$var wire 1 / clk $end
$var wire 1 $ reset $end
$var reg 1 0 Q $end
$upscope $end
$upscope $end
$upscope $end
$enddefinitions $end
$comment Show the parameter values. $end
$dumpall
$end
#0
$dumpvars
00
0/
1.
0-
0,
1+
0*
0)
1(
0'
1&
b0 %
0$
0#
0"
b0 !
$end
#2
1$
1#
1"
#4
1)
b1 !
b1 %
1'
0"
#6
1"
#8
1,
1*
0)
b10 !
b10 %
0'
0"
#10
1"
#12
1)
b11 !
b11 %
1'
0"
#14
1"
#16
1/
1-
0,
0*
0)
b100 !
b100 %
0'
0"
#18
1"
#20
1)
b101 !
b101 %
1'
0"
#22
1"
#24
1,
1*
0)
b110 !
b110 %
0'
0"
#26
1"
#28
1)
b111 !
b111 %
1'
0"
#30
1"
#32
10
0/
0-
0,
0*
0)
b1000 !
b1000 %
0'
0"
#34
1"
#36
1)
b1001 !
b1001 %
1'
0"
#38
1"
#40
00
1$
0,
0*
0)
b0 !
b0 %
0'
0"
#42
1"
#44
1)
b1 !
b1 %
1'
0"
#46
1"
#48
1,
1*
0)
b10 !
b10 %
0'
0"
#50
1"
#52
1)
b11 !
b11 %
1'
0"
#54
1"
#56
1/
1-
0,
0*
0)
b100 !
b100 %
0'
0"
#58
1"
#60
1)
b101 !
b101 %
1'
0"
#62
1"
#64
1,
1*
0)
b110 !
b110 %
0'
0"
#66
1"
#68
1)
b111 !
b111 %
1'
0"
#70
1"
#72
10
0/
0-
0,
0*
0)
b1000 !
b1000 %
0'
0"
#74
1"
#76
1)
b1001 !
b1001 %
1'
0"
#78
1"
#80
00
1$
0,
0*
0)
b0 !
b0 %
0'
0"
