pipo.v
module pipo(D,clk,Q,reset);
parameter n = 4;

input [3:0] D;
input clk,reset;
output reg[3:0] Q;

always @(posedge clk, posedge reset) begin
    if(reset) Q<= 4'b0000;
    else Q<=D;
end
endmodule

pipo_tb.v
`include "pipo.v"

module pipo_tb();

reg [3:0] D;
reg clk, reset;
wire [3:0] Q;

pipo pipo_ins(D,clk,Q,reset);

initial begin
    $dumpfile("pipo_tb.vcd");
    $dumpvars(0,pipo_tb);
end

initial begin
    clk = 0;
    forever #1 clk = ~clk;
end

initial begin
    reset = 1; D = 0; #2;
    reset = 0;
    D = 4; #2;
    D = 5; #2;
    D = 9; #2;
    D = 7; #2;
    $finish;
end
endmodule

pipo_tb.vcd
$date
	Tue Nov 04 13:46:58 2025
$end
$version
	Icarus Verilog
$end
$timescale
	1s
$end
$scope module pipo_tb $end
$var wire 4 ! Q [3:0] $end
$var reg 4 " D [3:0] $end
$var reg 1 # clk $end
$var reg 1 $ reset $end
$scope module pipo_ins $end
$var wire 4 % D [3:0] $end
$var wire 1 # clk $end
$var wire 1 $ reset $end
$var parameter 32 & n $end
$var reg 4 ' Q [3:0] $end
$upscope $end
$upscope $end
$enddefinitions $end
$comment Show the parameter values. $end
$dumpall
b100 &
$end
#0
$dumpvars
b0 '
b0 %
1$
0#
b0 "
b0 !
$end
#1
1#
#2
0#
b100 "
b100 %
0$
#3
b100 !
b100 '
1#
#4
0#
b101 "
b101 %
#5
b101 !
b101 '
1#
#6
0#
b1001 "
b1001 %
#7
b1001 !
b1001 '
1#
#8
0#
b111 "
b111 %
#9
b111 !
b111 '
1#
