priority4to2.v
module priority4to2(w,z,y);

input [3:0] w;
output reg [1:0] y;
output reg z;

always @(*) begin
    z = 1;
    casex(w)
        4'b1xxx: y = 3;
        4'b01xx: y = 2;
        4'b001x: y = 1;
        4'b0001: y = 0;
        default:
        begin
            z = 0;
            y = 2'bx;
        end
    endcase
end
endmodule

priority4to2_tb.v
`include "priority4to2.v"
`timescale 1ns/1ns

module priority4to2_tb();

reg [3:0] w;
wire z;
wire [1:0] y;

priority4to2 priority4to2_ins(w,z,y);

initial begin
    $dumpfile("priority4to2_tb.vcd");
    $dumpvars(0,priority4to2_tb);
end

initial begin
    for(integer i = 0; i<16; i++)begin
        w = i; #2;
    end
end
endmodule

priority4to2_tb.vcd
$date
	Wed Nov 05 11:35:14 2025
$end
$version
	Icarus Verilog
$end
$timescale
	1ns
$end
$scope module priority4to2_tb $end
$var wire 1 ! z $end
$var wire 2 " y [1:0] $end
$var reg 4 # w [3:0] $end
$scope module priority4to2_ins $end
$var wire 4 $ w [3:0] $end
$var reg 2 % y [1:0] $end
$var reg 1 ! z $end
$upscope $end
$scope begin $ivl_for_loop0 $end
$var integer 32 & i [31:0] $end
$upscope $end
$upscope $end
$enddefinitions $end
$comment Show the parameter values. $end
$dumpall
$end
#0
$dumpvars
b0 &
bx %
b0 $
b0 #
bx "
0!
$end
#2
b0 "
b0 %
1!
b1 #
b1 $
b1 &
#4
b1 "
b1 %
b10 #
b10 $
b10 &
#6
b11 #
b11 $
b11 &
#8
b10 "
b10 %
b100 #
b100 $
b100 &
#10
b101 #
b101 $
b101 &
#12
b110 #
b110 $
b110 &
#14
b111 #
b111 $
b111 &
#16
b11 "
b11 %
b1000 #
b1000 $
b1000 &
#18
b1001 #
b1001 $
b1001 &
#20
b1010 #
b1010 $
b1010 &
#22
b1011 #
b1011 $
b1011 &
#24
b1100 #
b1100 $
b1100 &
#26
b1101 #
b1101 $
b1101 &
#28
b1110 #
b1110 $
b1110 &
#30
b1111 #
b1111 $
b1111 &
#32
b10000 &
