DFF.v
//+ve edge, async active high reset
module DFF(D,clk,Q,reset,preset);
input D,clk,reset,preset;
output reg Q;

always @(posedge clk, posedge reset, posedge preset) begin
    if(reset) Q<=0;
    else if(preset) Q<=1'b1;
    else begin
        Q<=D;
    end
end
endmodule

ringcounter.v
`include "DFF.v"
module ringcounter(clk,Q,reset,preset);
input clk,reset,preset;
output [3:0]Q;

DFF DFF_ins1(Q[0],clk,Q[3],reset,preset);
DFF DFF_ins2(Q[3],clk,Q[2],reset,1'b0);
DFF DFF_ins3(Q[2],clk,Q[1],reset,1'b0);
DFF DFF_ins4(Q[1],clk,Q[0],reset,1'b0);

endmodule

ringcounter_tb.v
`include "ringcounter.v"
`timescale 1ns/1ns

module ringcounter_tb();

reg clk, reset, preset;
wire [3:0]Q;

ringcounter ringcounter_ins(clk,Q,reset,preset);

initial begin
    $dumpfile("ringcounter_tb.vcd");
    $dumpvars(0,ringcounter_tb);
end

initial begin
    clk = 0;
    forever #2 clk = ~clk;
end

initial begin
    reset = 1; preset = 0; #2;  
    reset = 0; preset = 1; #2;
    reset = 0; preset = 0; #40;
    $finish;
end
endmodule

ringcounter_tb.vcd
$date
	Wed Nov 05 02:24:36 2025
$end
$version
	Icarus Verilog
$end
$timescale
	1ns
$end
$scope module ringcounter_tb $end
$var wire 4 ! Q [3:0] $end
$var reg 1 " clk $end
$var reg 1 # preset $end
$var reg 1 $ reset $end
$scope module ringcounter_ins $end
$var wire 1 " clk $end
$var wire 1 # preset $end
$var wire 1 $ reset $end
$var wire 4 % Q [3:0] $end
$scope module DFF_ins1 $end
$var wire 1 & D $end
$var wire 1 " clk $end
$var wire 1 # preset $end
$var wire 1 $ reset $end
$var reg 1 ' Q $end
$upscope $end
$scope module DFF_ins2 $end
$var wire 1 ( D $end
$var wire 1 " clk $end
$var wire 1 ) preset $end
$var wire 1 $ reset $end
$var reg 1 * Q $end
$upscope $end
$scope module DFF_ins3 $end
$var wire 1 + D $end
$var wire 1 " clk $end
$var wire 1 , preset $end
$var wire 1 $ reset $end
$var reg 1 - Q $end
$upscope $end
$scope module DFF_ins4 $end
$var wire 1 . D $end
$var wire 1 " clk $end
$var wire 1 / preset $end
$var wire 1 $ reset $end
$var reg 1 0 Q $end
$upscope $end
$upscope $end
$upscope $end
$enddefinitions $end
$comment Show the parameter values. $end
$dumpall
$end
#0
$dumpvars
00
0/
0.
0-
0,
0+
0*
0)
0(
0'
0&
b0 %
1$
0#
0"
b0 !
$end
#2
1(
b1000 !
b1000 %
1'
1#
0$
1"
#4
0#
0"
#6
0(
1+
0'
b100 !
b100 %
1*
1"
#8
0"
#10
0+
1.
0*
b10 !
b10 %
1-
1"
#12
0"
#14
0.
1&
0-
b1 !
b1 %
10
1"
#16
0"
#18
1(
0&
1'
b1000 !
b1000 %
00
1"
#20
0"
#22
0(
1+
0'
b100 !
b100 %
1*
1"
#24
0"
#26
0+
1.
0*
b10 !
b10 %
1-
1"
#28
0"
#30
0.
1&
0-
b1 !
b1 %
10
1"
#32
0"
#34
1(
0&
1'
b1000 !
b1000 %
00
1"
#36
0"
#38
0(
1+
0'
b100 !
b100 %
1*
1"
#40
0"
#42
0+
1.
0*
b10 !
b10 %
1-
1"
