TFF.v
module TFF(T,clk,Q,reset);
input T,clk,reset;
output reg Q;

always @(negedge clk, negedge reset)begin
    if(!reset) Q<=0;
    else begin
        if(T==0) Q<=Q;
        else Q<=~Q;
    end
end
endmodule

TFF_tb.v
`include "TFF.v"
`timescale 1ns/1ns

module TFF_tb();

reg T,clk,reset;
wire Q;

TFF TFF_ins(T,clk,Q,reset);

initial begin
    $dumpfile("TFF_tb.vcd");
    $dumpvars(0,TFF_tb);
end

initial begin
    clk = 0;
    forever #2 clk = ~clk;
end

initial begin
    reset = 0; T = 0; #2;
    reset = 0; T = 1; #2;

    reset = 1; T = 1; #5;
    reset = 1; T = 0; #5;
    reset = 1; T = 0; #5;
    reset = 1; T = 1; #5;
    $finish;
end
endmodule

TFF_tb.vcd
$date
	Tue Nov 04 12:34:11 2025
$end
$version
	Icarus Verilog
$end
$timescale
	1ns
$end
$scope module TFF_tb $end
$var wire 1 ! Q $end
$var reg 1 " T $end
$var reg 1 # clk $end
$var reg 1 $ reset $end
$scope module TFF_ins $end
$var wire 1 " T $end
$var wire 1 # clk $end
$var wire 1 $ reset $end
$var reg 1 ! Q $end
$upscope $end
$upscope $end
$enddefinitions $end
$comment Show the parameter values. $end
$dumpall
$end
#0
$dumpvars
0$
0#
0"
0!
$end
#2
1"
1#
#4
1!
1$
0#
#6
1#
#8
0!
0#
#9
0"
#10
1#
#12
0#
#14
1#
#16
0#
#18
1#
#19
1"
#20
1!
0#
#22
1#
#24
0!
0#
